hunspellcheck/__init__.py
hunspellcheck/exceptions.py
hunspellcheck/spellchecker.py
hunspellcheck/word.py
hunspellcheck/cli/__init__.py
hunspellcheck/cli/files.py
hunspellcheck/cli/languages.py
hunspellcheck/cli/personal_dicts.py
hunspellcheck/cli/version.py
hunspellcheck/hunspell/__init__.py
hunspellcheck/hunspell/dictionaries.py
hunspellcheck/hunspell/spellcheck.py
hunspellcheck/hunspell/version.py
hunspellcheck-0.1.0.dist-info/LICENSE
hunspellcheck-0.1.0.dist-info/METADATA
hunspellcheck-0.1.0.dist-info/WHEEL
hunspellcheck-0.1.0.dist-info/top_level.txt
hunspellcheck-0.1.0.dist-info/RECORD
