Metadata-Version: 2.1
Name: hunspellcheck
Version: 0.1.0
Summary: Spell checkers builder using hunspell.
Home-page: https://github.com/mondeja/hunspellcheck
Author: Álvaro Mondéjar Rubio
Author-email: mondejar1994@gmail.com
License: BSD-3-Clause
Project-URL: Documentation, https://github.com/mondeja/hunspellcheck#documentation
Project-URL: GitHub Project, https://github.com/mondeja/hunspellcheck
Project-URL: Issue Tracker, https://github.com/mondeja/hunspellcheck/issues
Platform: UNKNOWN
Classifier: License :: OSI Approved :: BSD License
Classifier: Programming Language :: Python
Classifier: Programming Language :: Python :: 3
Classifier: Programming Language :: Python :: 3 :: Only
Classifier: Programming Language :: Python :: 3.7
Classifier: Programming Language :: Python :: 3.8
Classifier: Programming Language :: Python :: 3.9
Classifier: Programming Language :: Python :: 3.10
Classifier: Programming Language :: Python :: 3.11
Requires-Python: >=3.7
Requires-Dist: jinja2[i18n]
Provides-Extra: dev
Requires-Dist: Sphinx (==4.5.0) ; extra == 'dev'
Requires-Dist: pytest-cov (==4.0.0) ; extra == 'dev'
Requires-Dist: pytest (==7.2.0) ; extra == 'dev'
Requires-Dist: sphinx-github-changelog (==1.2.0) ; extra == 'dev'
Requires-Dist: sphinx-rtd-theme (==0.5.2) ; extra == 'dev'
Requires-Dist: yamllint (==1.26.1) ; extra == 'dev'
Provides-Extra: doc
Requires-Dist: Sphinx (==4.5.0) ; extra == 'doc'
Requires-Dist: sphinx-github-changelog (==1.2.0) ; extra == 'doc'
Requires-Dist: sphinx-rtd-theme (==0.5.2) ; extra == 'doc'
Provides-Extra: test
Requires-Dist: pytest (==7.2.0) ; extra == 'test'
Requires-Dist: pytest-cov (==4.0.0) ; extra == 'test'
